{
  "post": "Estilo impecable, corte exclusivo — Story de servicios (navaja / tijera / máquina)",
  "build_method": "Opción B (ver carousel-tile-generation.md): fondo generado sin texto vía scripts/kie_image_gen.py (kie.ai gpt-image-2-text-to-image, aspect_ratio 9:16, resolution 2K) guardado en assets/bg.png -- barbero de perfil trabajando un fade con máquina, duotono B/N con luz clave dorada en la línea del fade. Compuesto con texto/logo reales en index.html y renderizado con Chrome headless a 00-story.png (2160x3840, 2x de 1080x1920). Inspirado en un post de referencia de otra barbería (estilo collage/papel rasgado, fondo amarillo dominante, tres tags de servicio). Tres excepciones deliberadas al sistema de marca, aprobadas por el usuario: (1) Nordic Yellow domina ~70% del layout como fondo sólido en vez de ser solo un acento 10-15%; (2) las tarjetas usan bordes de papel rasgado (clip-path irregular generado con jitter aleatorio en Python, ver historial) en vez de los cortes angulares tipo cuchilla usados en la excepción anterior (cuidado-de-barba) -- el usuario pidió explícitamente el look rasgado/collage fiel a la referencia, no la variante angular; (3) capa de textura superior con el wordmark repetido a gran escala y rotado, recortado por una tarjeta de papel superpuesta. El resto respeta el sistema: headline en Lost in South con una sola palabra resaltada (EXCLUSIVO en Yellow Deep #C9A400), íconos de servicio dibujados en SVG monocromático ink-black (no emoji a color, para no romper la paleta de tres tonos), una única frase de firma en Lost in South ('Cada corte, forjado con precisión.' — nueva línea de posicionamiento en español, reemplaza a 'Forged for the close cut.' en design-system.md/html) llenando el espacio antes de la barra de contacto, logo real (Nordic-BarberShop-logo-black.png, tinta única sobre fondo claro por la regla de uso del logo) y CTA de WhatsApp con el número real 2260-9101 (mismo dato usado en cambio-numero-whatsapp).",
  "headline": "ESTILO IMPECABLE, CORTE EXCLUSIVO",
  "headline_highlight": "EXCLUSIVO",
  "services": ["Corte a navaja", "Corte a tijera", "Corte a máquina"],
  "caption_on_image": "2260-9101 · Agenda tu cita por WhatsApp",
  "instagram_caption": "Estilo impecable, cortes exclusivos. 💈\n\nEn Nordic trabajamos a tu medida: navaja, tijera o máquina — el corte que se ajuste a vos, siempre con la misma precisión.\n\nAgenda tu cita al 2260-9101. Te esperamos.\n\n#NordicBarberShop #GuatemalaBarbershop #CorteExclusivo",
  "file": "00-story.png"
}
